{
  "heads/barrels.yml": 45,
  "heads/books.yml": 76,
  "heads/bottles.yml": 13,
  "heads/buckets.yml": 27,
  "heads/bundles.yml": 33,
  "heads/candles.yml": 85,
  "heads/chalices.yml": 17,
  "heads/mini_blocks.yml": 356,
  "heads/pumpkins.yml": 24,
  "heads/alphabet/oak.yml": 192,
  "heads/alphabet/birch.yml": 133,
  "heads/alphabet/spruce.yml": 133,
  "heads/alphabet/jungle.yml": 135,
  "heads/alphabet/cherry_planks.yml": 157,
  "heads/alphabet/mangrove_planks.yml": 157,
  "heads/alphabet/cobblestone.yml": 132,
  "heads/alphabet/diamond.yml": 134,
  "heads/alphabet/emerald.yml": 70,
  "heads/alphabet/gold.yml": 153,
  "heads/alphabet/iron.yml": 24,
  "heads/alphabet/quartz.yml": 133,
  "heads/alphabet/ice.yml": 130,
  "heads/alphabet/dirt.yml": 133,
  "total": 2492
}